cinquillo/__init__.py
cinquillo/bot_jugador.py
cinquillo/carta.py
cinquillo/jugador.py
cinquillo/mesa.py
cinquillo/motor.py
cinquillo/partida.py
cinquillo/reglas.py
cinquillo_core-0.1.0.dist-info/LICENSE
cinquillo_core-0.1.0.dist-info/METADATA
cinquillo_core-0.1.0.dist-info/WHEEL
cinquillo_core-0.1.0.dist-info/RECORD
