Metadata-Version: 2.3
Name: cinquillo-core
Version: 0.1.0
Summary: Motor del juego Cinquillo para simulaciones y desarrollo de IA.
License: MIT
Author: Tu Nombre
Author-email: tucorreo@example.com
Requires-Python: >=3.10,<4.0
Classifier: License :: OSI Approved :: MIT License
Classifier: Programming Language :: Python :: 3
Classifier: Programming Language :: Python :: 3.10
Classifier: Programming Language :: Python :: 3.11
Classifier: Programming Language :: Python :: 3.12
Classifier: Programming Language :: Python :: 3.13
